ufostroker-0.3.0.dist-info/METADATA
ufostroker-0.3.0.dist-info/WHEEL
ufostroker/__init__.py
ufostroker/ufostroker.abi3.so
ufostroker-0.3.0.dist-info/RECORD
