Metadata-Version: 2.1
Name: ufostroker
Version: 0.3.0
Requires-Dist: ufo2ft
Requires-Dist: beziers >=0.4.0
Summary: Python wrapper around the MFEKmath library
Author: Simon Cozens <simon@simon-cozens.org>
Author-email: Simon Cozens <simon@simon-cozens.org>
Project-URL: Source Code, https://github.com/simoncozens/ufostroker-py
